wagtail_images_deduplicator/__init__.py
wagtail_images_deduplicator/apps.py
wagtail_images_deduplicator/checks.py
wagtail_images_deduplicator/find_duplicates.py
wagtail_images_deduplicator/hash_functions.py
wagtail_images_deduplicator/models.py
wagtail_images_deduplicator/utils.py
wagtail_images_deduplicator/migrations/__init__.py
wagtail_images_deduplicator-1.0a1.dist-info/LICENSE
wagtail_images_deduplicator-1.0a1.dist-info/METADATA
wagtail_images_deduplicator-1.0a1.dist-info/WHEEL
wagtail_images_deduplicator-1.0a1.dist-info/top_level.txt
wagtail_images_deduplicator-1.0a1.dist-info/RECORD
