Metadata-Version: 2.1
Name: wagtail-images-deduplicator
Version: 1.0a1
Summary: Detect duplicates in the Wagtail images library.
Home-page: https://github.com/tijani-dia/wagtail-images-deduplicator/
Author: Tidiane Dia, Jacob Topp-Mugglestone
Author-email: atdia97@gmail.com
License: BSD-3-Clause
Project-URL: Source, https://github.com/tijani-dia/wagtail-images-deduplicator/
Project-URL: Issue tracker, https://github.com/tijani-dia/wagtail-images-deduplicator/issues/
Classifier: Development Status :: 3 - Alpha
Classifier: Environment :: Web Environment
Classifier: Intended Audience :: Developers
Classifier: License :: OSI Approved :: BSD License
Classifier: Programming Language :: Python :: 3
Classifier: Framework :: Django
Classifier: Framework :: Wagtail
Classifier: Topic :: Internet :: WWW/HTTP
Requires-Python: >=3.7
License-File: LICENSE
Requires-Dist: wagtail (<5.0,>=3.0)
Requires-Dist: imagehash
Provides-Extra: build
Requires-Dist: twine ; extra == 'build'
Requires-Dist: check-wheel-contents ; extra == 'build'
Provides-Extra: test
Requires-Dist: pytest ; extra == 'test'
Requires-Dist: pytest-cov ; extra == 'test'
Requires-Dist: pytest-django ; extra == 'test'
Requires-Dist: black ; extra == 'test'
Requires-Dist: isort ; extra == 'test'
Requires-Dist: flake8 ; extra == 'test'
Requires-Dist: dj-database-url ; extra == 'test'
